src/__init__.py
src/server.py
tests/__init__.py
tests/test_server.py
iflow_mcp_jensenloke_mssql_mcp_server-1.0.1.dist-info/METADATA
iflow_mcp_jensenloke_mssql_mcp_server-1.0.1.dist-info/WHEEL
iflow_mcp_jensenloke_mssql_mcp_server-1.0.1.dist-info/entry_points.txt
iflow_mcp_jensenloke_mssql_mcp_server-1.0.1.dist-info/top_level.txt
iflow_mcp_jensenloke_mssql_mcp_server-1.0.1.dist-info/RECORD
