Metadata-Version: 2.4
Name: iflow-mcp_jensenloke_mssql-mcp-server
Version: 1.0.1
Summary: A Model Context Protocol server for Microsoft SQL Server databases
Home-page: https://github.com/your-username/mssql-mcp-server
Author: MSSQL MCP Server
Author-email: 
Classifier: Development Status :: 4 - Beta
Classifier: Intended Audience :: Developers
Classifier: License :: OSI Approved :: MIT License
Classifier: Operating System :: OS Independent
Classifier: Programming Language :: Python :: 3
Classifier: Programming Language :: Python :: 3.8
Classifier: Programming Language :: Python :: 3.9
Classifier: Programming Language :: Python :: 3.10
Classifier: Programming Language :: Python :: 3.11
Classifier: Programming Language :: Python :: 3.12
Requires-Python: >=3.8
Requires-Dist: pyodbc>=4.0.39
Requires-Dist: pydantic>=2.0.0
Requires-Dist: python-dotenv>=1.0.1
Requires-Dist: mcp>=1.2.0
Requires-Dist: anyio>=4.5.0
Requires-Dist: asyncio-mqtt>=0.16.2
Requires-Dist: pytest>=7.0.0
Requires-Dist: pytest-asyncio>=0.21.0
Dynamic: author
Dynamic: classifier
Dynamic: description
Dynamic: description-content-type
Dynamic: home-page
Dynamic: requires-dist
Dynamic: requires-python
Dynamic: summary
